pycloud_client/__init__.py
pycloud_client/client.py
pycloud_client/utils.py
pycloud_client/proto/__init__.py
pycloud_client/proto/pycloud.proto
pycloud_client/proto/pycloud_pb2.py
pycloud_client/proto/pycloud_pb2_grpc.py
pycloud_client-0.7.1.dist-info/LICENSE.txt
pycloud_client-0.7.1.dist-info/METADATA
pycloud_client-0.7.1.dist-info/WHEEL
pycloud_client-0.7.1.dist-info/top_level.txt
pycloud_client-0.7.1.dist-info/RECORD
