Metadata-Version: 2.1
Name: pycloud-client
Version: 0.7.1
Summary: Connectors for PyCloud clusters
Home-page: https://pycloud.ai
Author: pycloud.ai
Author-email: contact@pycloud.ai
License: Apache 2.0
Platform: UNKNOWN
Requires-Dist: setuptools
Requires-Dist: docopt
Requires-Dist: json-tricks (==3.13.2)
Requires-Dist: requests (==2.23.0)
Requires-Dist: grpcio (==1.26.0)
Requires-Dist: protobuf (==3.9.2)
